LICENSE
MANIFEST.in
README.rst
setup.cfg
setup.py
examples/hiding.py
examples/myapp.py
examples/myapp2.py
tests/__init__.py
tests/test_widget.py
tw2/__init__.py
tw2.dynforms.egg-info/PKG-INFO
tw2.dynforms.egg-info/SOURCES.txt
tw2.dynforms.egg-info/dependency_links.txt
tw2.dynforms.egg-info/entry_points.txt
tw2.dynforms.egg-info/namespace_packages.txt
tw2.dynforms.egg-info/not-zip-safe
tw2.dynforms.egg-info/requires.txt
tw2.dynforms.egg-info/top_level.txt
tw2/dynforms/__init__.py
tw2/dynforms/samples.py
tw2/dynforms/widgets.py
tw2/dynforms/static/ajax_lookup.js
tw2/dynforms/static/del.png
tw2/dynforms/static/dynforms.js
tw2/dynforms/static/hide-hover.png
tw2/dynforms/static/hide.png
tw2/dynforms/static/office-calendar.png
tw2/dynforms/static/show-hover.png
tw2/dynforms/static/show.png
tw2/dynforms/static/tw2dynforms.css
tw2/dynforms/static/tw2dynforms.js
tw2/dynforms/static/undo.png
tw2/dynforms/static/calendar/calendar-blue.css
tw2/dynforms/static/calendar/calendar-blue2.css
tw2/dynforms/static/calendar/calendar-brown.css
tw2/dynforms/static/calendar/calendar-green.css
tw2/dynforms/static/calendar/calendar-setup.js
tw2/dynforms/static/calendar/calendar-system.css
tw2/dynforms/static/calendar/calendar-tas.css
tw2/dynforms/static/calendar/calendar-win2k-1.css
tw2/dynforms/static/calendar/calendar-win2k-2.css
tw2/dynforms/static/calendar/calendar-win2k-cold-1.css
tw2/dynforms/static/calendar/calendar-win2k-cold-2.css
tw2/dynforms/static/calendar/calendar.js
tw2/dynforms/static/calendar/menuarrow.gif
tw2/dynforms/static/calendar/menuarrow2.gif
tw2/dynforms/static/calendar/lang/calendar-af.js
tw2/dynforms/static/calendar/lang/calendar-bg-cp1251.js
tw2/dynforms/static/calendar/lang/calendar-bg.js
tw2/dynforms/static/calendar/lang/calendar-ca.js
tw2/dynforms/static/calendar/lang/calendar-cs-cp1250.js
tw2/dynforms/static/calendar/lang/calendar-cs.js
tw2/dynforms/static/calendar/lang/calendar-da.js
tw2/dynforms/static/calendar/lang/calendar-de.js
tw2/dynforms/static/calendar/lang/calendar-de_at.js
tw2/dynforms/static/calendar/lang/calendar-de_de.js
tw2/dynforms/static/calendar/lang/calendar-el.js
tw2/dynforms/static/calendar/lang/calendar-en.js
tw2/dynforms/static/calendar/lang/calendar-es.js
tw2/dynforms/static/calendar/lang/calendar-fi.js
