Metadata-Version: 1.1
Name: tw2.dynforms
Version: 2.0.1
Summary: Dynamic widgets with JavaScript for ToscaWidgets 2
Home-page: http://toscawidgets.org/documentation/tw2.core/
Author: Paul Johnston & Contributors
Author-email: paj@pajhome.org.uk
License: MIT
Keywords: toscawidgets.widgets
Platform: UNKNOWN
Classifier: Development Status :: 5 - Production/Stable
Classifier: Environment :: Web Environment
Classifier: Environment :: Web Environment :: ToscaWidgets
Classifier: Topic :: Software Development :: Libraries :: Python Modules
Classifier: Topic :: Software Development :: Widget Sets
Classifier: Intended Audience :: Developers
Classifier: Operating System :: OS Independent
Classifier: Programming Language :: Python
